raise_synthetic_data_generator/__init__.py
raise_synthetic_data_generator/custom_exceptions.py
raise_synthetic_data_generator/config/logger.py
raise_synthetic_data_generator/sd_evaluation/__init__.py
raise_synthetic_data_generator/sd_evaluation/fidelity_evaluation_table.csv
raise_synthetic_data_generator/sd_evaluation/synthetic_data_evaluation.py
raise_synthetic_data_generator/sd_evaluation/evaluation_report/ReportTemplate.py
raise_synthetic_data_generator/sd_evaluation/evaluation_report/__global_variables__.py
raise_synthetic_data_generator/sd_evaluation/evaluation_report/__init__.py
raise_synthetic_data_generator/sd_evaluation/evaluation_report/report.py
raise_synthetic_data_generator/sd_evaluation/evaluation_report/images/EOSC-RAISE.png
raise_synthetic_data_generator/sd_evaluation/evaluation_report/pdf_styles/__init__.py
raise_synthetic_data_generator/sd_evaluation/evaluation_report/pdf_styles/paragraph_styles.py
raise_synthetic_data_generator/sd_evaluation/evaluation_report/pdf_styles/table_styles.py
raise_synthetic_data_generator/sd_evaluation/fidelity_metrics/__init__.py
raise_synthetic_data_generator/sd_evaluation/fidelity_metrics/correlations.py
raise_synthetic_data_generator/sd_evaluation/fidelity_metrics/dimensionality_reduction.py
raise_synthetic_data_generator/sd_evaluation/fidelity_metrics/distributions.py
raise_synthetic_data_generator/sd_evaluation/fidelity_metrics/ml_metrics.py
raise_synthetic_data_generator/sd_evaluation/fidelity_metrics/statistical_tests.py
raise_synthetic_data_generator/sd_evaluation/fidelity_metrics/visualizations.py
raise_synthetic_data_generator/sdg_models/AbstractModel.py
raise_synthetic_data_generator/sdg_models/CTGANModel.py
raise_synthetic_data_generator/sdg_models/GaussianCopulaModel.py
raise_synthetic_data_generator/sdg_models/TVAEModel.py
raise_synthetic_data_generator/sdg_models/__init__.py
raise_synthetic_data_generator/synthetic_data_generator/__init__.py
raise_synthetic_data_generator-0.1.11.dist-info/licenses/LICENSE
raise_synthetic_data_generator-0.1.11.dist-info/METADATA
raise_synthetic_data_generator-0.1.11.dist-info/WHEEL
raise_synthetic_data_generator-0.1.11.dist-info/top_level.txt
raise_synthetic_data_generator-0.1.11.dist-info/RECORD
