Metadata-Version: 2.4
Name: raise-synthetic-data-generator
Version: 0.1.11
Summary: RAISE Synthetic data generator
Author-email: RAISE <info@raise-science.eu>
License: This program is licensed under the European Union Public License (EUPL) version 1.2.
Project-URL: Homepage, https://raise-science.eu/
Project-URL: Documentation, https://documentation.raise-science.eu/
Project-URL: Source, https://repo.raise-science.eu/raise_dev/raise-synthetic-data-generator
Classifier: Development Status :: 4 - Beta
Classifier: Intended Audience :: Science/Research
Classifier: Topic :: Scientific/Engineering :: Artificial Intelligence
Classifier: License :: OSI Approved :: European Union Public Licence 1.2 (EUPL 1.2)
Classifier: Programming Language :: Python :: 3
Requires-Python: >=3.9
License-File: LICENSE
Requires-Dist: phik==0.12.4
Requires-Dist: reportlab==4.2.2
Requires-Dist: sdv==1.13.1
Requires-Dist: seaborn==0.13.2
Requires-Dist: setuptools==57.5.0
Requires-Dist: visions==0.7.6
Requires-Dist: wheel==0.43.0
Requires-Dist: anonymeter
Requires-Dist: inflect
Requires-Dist: matplotlib
Requires-Dist: mkdocs
Requires-Dist: mkdocstrings[crystal,python]
Requires-Dist: numpy
Requires-Dist: opentsne
Requires-Dist: pandas
Requires-Dist: plotly
Requires-Dist: scipy
Requires-Dist: scikit-learn
Requires-Dist: umap
Requires-Dist: umap-learn
Requires-Dist: utils
Requires-Dist: optuna
Dynamic: license-file
